COPYING.txt
INSTALL.txt
MANIFEST.in
requirements-dev.txt
requirements.txt
setup.cfg
setup.py
Divisi2.egg-info/PKG-INFO
Divisi2.egg-info/SOURCES.txt
Divisi2.egg-info/dependency_links.txt
Divisi2.egg-info/requires.txt
Divisi2.egg-info/top_level.txt
divisi2/__init__.py
divisi2/blending.py
divisi2/ccipca.py
divisi2/dataset.py
divisi2/dense.py
divisi2/examples.py
divisi2/exceptions.py
divisi2/export_svdview.py
divisi2/fileIO.py
divisi2/labels.py
divisi2/network.py
divisi2/operators.py
divisi2/ordered_set.py
divisi2/priodict.py
divisi2/reconstructed.py
divisi2/sparse.py
divisi2/algorithms/__init__.py
divisi2/algorithms/mds.py
divisi2/algorithms/nmf.py
divisi2/algorithms/randomized_svd.py
divisi2/algorithms/svd.py
divisi2/data/augment_conceptnet.py
divisi2/data/eval/usertest_data.pickle
divisi2/data/graphs/conceptnet_en.graph.gz
divisi2/data/graphs/conceptnet_ja.graph.gz
divisi2/data/matrices/conceptnet_assoc_en.gz
divisi2/data/matrices/conceptnet_assoc_ja.gz
divisi2/data/matrices/conceptnet_en.gz
divisi2/data/matrices/conceptnet_ja.gz
divisi2/test/__init__.py
divisi2/test/ordercompare.py
divisi2/test/test_dense.py
divisi2/test/test_pickle.py
divisi2/test/test_priodict.py
divisi2/test/test_sparse.py
divisi2/test/test_svd.py
divisi2/test/test_tfidf.py
divisi2/test/eval/__init__.py
divisi2/test/eval/test_predictions.py
doc/conf.py
doc/_static/jsMath/COPYING.txt
svdlib/_svdlib.c
svdlib/_svdlib.pyx
svdlib/las2.c
svdlib/ll_mat.h
svdlib/svdlib.c
svdlib/svdlib.h
svdlib/svdutil.c
svdlib/svdutil.h
svdlib/svdwrapper.c
svdlib/svdwrapper.h